pybpod_alyx_module/__init__.py
pybpod_alyx_module/alyx_details.py
pybpod_alyx_module/module.py
pybpod_alyx_module/module_api.py
pybpod_alyx_module/module_gui.py
pybpod_alyx_module/settings.py
pybpod_alyx_module/alyxapi/__init__.py
pybpod_alyx_module/alyxapi/alyxapi.py
pybpod_alyx_module/alyxapi/alyxconf.py
pybpod_alyx_module/alyxapi/data/__init__.py
pybpod_alyx_module/alyxapi/data/data.py
pybpod_alyx_module/alyxapi/data/get.py
pybpod_alyx_module/alyxapi/data/post.py
pybpod_alyx_module/alyxapi/subjects/__init__.py
pybpod_alyx_module/alyxapi/subjects/get.py
pybpod_alyx_module/alyxapi/subjects/post.py
pybpod_alyx_module/alyxapi/subjects/subjects.py
pybpod_alyx_module/models/__init__.py
pybpod_alyx_module/models/project/__init__.py
pybpod_alyx_module/models/project/project_treenode.py
pybpod_alyx_module/models/subject/__init__.py
pybpod_alyx_module/models/subject/alyx_subject.py
pybpod_alyx_module/models/user/__init__.py
pybpod_alyx_module/models/user/user_window.py
pybpod_gui_plugin_alyx-1.1.2.dist-info/METADATA
pybpod_gui_plugin_alyx-1.1.2.dist-info/WHEEL
pybpod_gui_plugin_alyx-1.1.2.dist-info/top_level.txt
pybpod_gui_plugin_alyx-1.1.2.dist-info/RECORD
